banner_hun0219/__init__.py
banner_hun0219/banner.py
banner_hun0219-0.3.3.dist-info/METADATA
banner_hun0219-0.3.3.dist-info/WHEEL
banner_hun0219-0.3.3.dist-info/entry_points.txt
banner_hun0219-0.3.3.dist-info/top_level.txt
banner_hun0219-0.3.3.dist-info/RECORD
