Metadata-Version: 2.1
Name: banner_hun0219
Version: 0.3.3
Summary: banner output program
Author-email: hun0219 <gsw98000@gmail.com>
License: MIT
Project-URL: Homepage, https://github.com/hun0219/banner_hun0219
Project-URL: Issues, https://github.com/hun0219/banner_hun0219/issues
Requires-Python: >=3.9
Requires-Dist: pyfiglet >=1.0.2
